{
    "status" : true,
    "arms":["img/HeatingStone.png","img/ProcessedClothing.png"],
    "pearlArms":["ProcessingSetGloves.png","ProcessingSetDress.png","ProcessingSetHeadwear.png","ProcessingSetShoes.png"],
    "method":[
        {
            "formula" : [
                {
                    "name" : "img/IronFragments.png",
                    "LoV"  : "img/LackValue.png"
                },
                {
                    "name" : "img/Coal.png",
                    "LoV"  : "img/LackValue.png"
                }
            ],
            "recycle" : ["img/Steel.png"]
        },{
            "formula" : [
                {
                    "name" : "img/IronOre.png",
                    "LoV"  : "img/LackValue.png"
                }
            ],
            "recycle" : ["img/IronFragments.png"]
        }
    ]
}